gemini_ocr/__init__.py
gemini_ocr/__main__.py
gemini_ocr/cli.py
gemini_ocr/config.py
gemini_ocr/processor.py
gemini_ocr/retry.py
gemini_ocr/utils.py
gemini_ocr_cli-0.2.1.dist-info/METADATA
gemini_ocr_cli-0.2.1.dist-info/WHEEL
gemini_ocr_cli-0.2.1.dist-info/entry_points.txt
gemini_ocr_cli-0.2.1.dist-info/licenses/LICENSE
gemini_ocr_cli-0.2.1.dist-info/RECORD
