Metadata-Version: 2.4
Name: gemini-ocr-cli
Version: 0.2.1
Summary: CLI tool for OCR processing using Google Gemini's vision capabilities
Project-URL: Homepage, https://github.com/r-uben/gemini-ocr-cli
Project-URL: Repository, https://github.com/r-uben/gemini-ocr-cli
Project-URL: Issues, https://github.com/r-uben/gemini-ocr-cli/issues
Author-email: Ruben Fernandez-Fuertes <fernandezfuertesruben@gmail.com>
License: MIT
License-File: LICENSE
Keywords: cli,document-processing,gemini,google,ocr,pdf,vision
Classifier: Development Status :: 4 - Beta
Classifier: Intended Audience :: Developers
Classifier: Intended Audience :: Science/Research
Classifier: License :: OSI Approved :: MIT License
Classifier: Operating System :: OS Independent
Classifier: Programming Language :: Python :: 3
Classifier: Programming Language :: Python :: 3.10
Classifier: Programming Language :: Python :: 3.11
Classifier: Programming Language :: Python :: 3.12
Classifier: Topic :: Scientific/Engineering :: Artificial Intelligence
Classifier: Topic :: Text Processing :: General
Requires-Python: >=3.10
Requires-Dist: click>=8.1.0
Requires-Dist: google-genai>=1.0.0
Requires-Dist: pillow>=10.0.0
Requires-Dist: pydantic-settings>=2.0.0
Requires-Dist: pydantic>=2.0.0
Requires-Dist: pymupdf>=1.24.0
Requires-Dist: python-dotenv>=1.0.0
Requires-Dist: rich>=13.0.0
Provides-Extra: dev
Requires-Dist: mypy>=1.0.0; extra == 'dev'
Requires-Dist: pytest-cov>=4.0.0; extra == 'dev'
Requires-Dist: pytest>=8.0.0; extra == 'dev'
Requires-Dist: ruff>=0.8.0; extra == 'dev'
